COPYING
MANIFEST.in
README.rst
bootstrap.py
buildout.cfg
setup.py
docs/conf.py
docs/index.rst
docs/scores.txt
docs/scores2.txt
xbob/__init__.py
xbob.measure.Bootstraps.egg-info/PKG-INFO
xbob.measure.Bootstraps.egg-info/SOURCES.txt
xbob.measure.Bootstraps.egg-info/dependency_links.txt
xbob.measure.Bootstraps.egg-info/entry_points.txt
xbob.measure.Bootstraps.egg-info/requires.txt
xbob.measure.Bootstraps.egg-info/top_level.txt
xbob.measure.Bootstraps.egg-info/zip-safe
xbob/measure/__init__.py
xbob/measure/Bootstraps/Bootstraps.py
xbob/measure/Bootstraps/__init__.py
xbob/measure/Bootstraps/test_error.py