Metadata-Version: 1.0
Name: xbob.measure.Bootstraps
Version: 0.0.1
Summary: The FAR-FRR confidence interval of the DET curve
Home-page: http://pypi.python.org/pypi/xbob.measure.Bootstraps
Author: Chi Ho CHAN
Author-email: chiho.chan@surrey.ac.uk
License: GPLv3
Platform: UNKNOWN
